rainbow/__init__.py
rainbow/fault_models.py
rainbow/leakage_models.py
rainbow/rainbow.py
rainbow/devices/__init__.py
rainbow/devices/stm32.py
rainbow/devices/stm32f215.pickle
rainbow/devices/stm32l4x1.pickle
rainbow/generics/__init__.py
rainbow/generics/aarch64.py
rainbow/generics/arm.py
rainbow/generics/cortexm.py
rainbow/generics/m68k.py
rainbow/generics/x64.py
rainbow/generics/x86.py
rainbow/loaders/__init__.py
rainbow/loaders/cleloader.py
rainbow/loaders/hexloader.py
rainbow/utils/__init__.py
rainbow/utils/color_functions.py
rainbow/utils/parse_svd.py
rainbow/utils/plot/__init__.py
rainbow/utils/plot/interface.py
donjon_rainbow-2.0.dist-info/METADATA
donjon_rainbow-2.0.dist-info/WHEEL
donjon_rainbow-2.0.dist-info/licenses/LICENSE
donjon_rainbow-2.0.dist-info/RECORD
