Metadata-Version: 2.3
Name: donjon-rainbow
Version: 2.0
Summary: Generic Unicorn tracer for side-channels and fault injection
Project-URL: Homepage, https://github.com/Ledger-Donjon/rainbow
Project-URL: Issues, https://github.com/Ledger-Donjon/rainbow/issues
Author: Alexandre Iooss, Ján Jančár
Author-email: Victor Servant <yhql.gh@gmail.com>
License-File: LICENSE
Classifier: Development Status :: 4 - Beta
Classifier: Intended Audience :: Developers
Classifier: Intended Audience :: Science/Research
Classifier: License :: OSI Approved :: GNU Lesser General Public License v3 or later (LGPLv3+)
Classifier: Programming Language :: Python :: 3
Classifier: Topic :: Security
Classifier: Topic :: Security :: Cryptography
Classifier: Topic :: System :: Emulators
Requires-Python: >=3.7
Requires-Dist: capstone>=4.0.0
Requires-Dist: cle>=9.2
Requires-Dist: intelhex
Requires-Dist: numpy
Requires-Dist: pygments
Requires-Dist: pyqt5
Requires-Dist: unicorn>=2.0.1
